setup.py
django_themagicapi.egg-info/PKG-INFO
django_themagicapi.egg-info/SOURCES.txt
django_themagicapi.egg-info/dependency_links.txt
django_themagicapi.egg-info/requires.txt
django_themagicapi.egg-info/top_level.txt
themagicapi/__init__.py
themagicapi/admin.py
themagicapi/apps.py
themagicapi/models.py
themagicapi/tests.py
themagicapi/urls.py
themagicapi/views.py
themagicapi/controller/__init__.py
themagicapi/controller/addcontroller.py
themagicapi/controller/filecontroller.py
themagicapi/controller/getcontroller.py
themagicapi/controller/rmcontroller.py
themagicapi/migrations/0001_initial.py
themagicapi/migrations/__init__.py