Metadata-Version: 1.0
Name: django-themagicapi
Version: 1.0.34
Summary: Django application. To launch an api server without endpoint. Create the database on demand
Home-page: https://github.com/vallemrv/django-themagicapi.git
Author: Manuel Rodriguez
Author-email: valle.mrv@gmail.com
License: Apache License, Version 2.0
Platform: UNKNOWN
